spotsweeper/__init__.py
spotsweeper/local_outliers.py
spotsweeper/plot_QC.py
spotsweeper/plot_QCpdf.py
spotsweeper-1.0.0.dist-info/licenses/LICENSE.txt
spotsweeper-1.0.0.dist-info/METADATA
spotsweeper-1.0.0.dist-info/WHEEL
spotsweeper-1.0.0.dist-info/top_level.txt
spotsweeper-1.0.0.dist-info/RECORD
