Metadata-Version: 2.4
Name: spotsweeper
Version: 1.0.0
Summary: Spatially-aware quality control for spatial transcriptomics
Home-page: https://github.com/danielchen05/spotsweeper_py
Author: Daniel Chen
Author-email: xchen274@jh.edu
License: MIT
Project-URL: Documentation, https://github.com/danielchen05/spotsweeper_py/
Project-URL: Source, https://github.com/danielchen05/spotsweeper_py/
Platform: any
Classifier: Development Status :: 4 - Beta
Classifier: Programming Language :: Python
Requires-Python: >=3.8
License-File: LICENSE.txt
Requires-Dist: importlib-metadata; python_version < "3.8"
Requires-Dist: numpy
Requires-Dist: pandas
Requires-Dist: scikit-learn
Requires-Dist: anndata
Requires-Dist: matplotlib
Provides-Extra: testing
Requires-Dist: setuptools; extra == "testing"
Requires-Dist: pytest; extra == "testing"
Requires-Dist: pytest-cov; extra == "testing"
Dynamic: license-file
